stitchclient/__init__.py
stitchclient/client.py
tests/__init__.py
tests/test_client.py
transit/__init__.py
transit/class_hash.py
transit/constants.py
transit/decoder.py
transit/helpers.py
transit/pyversion.py
transit/read_handlers.py
transit/reader.py
transit/rolling_cache.py
transit/sosjson.py
transit/transit_types.py
transit/write_handlers.py
transit/writer.py
stitchclient-1.0.0.dist-info/LICENSE
stitchclient-1.0.0.dist-info/METADATA
stitchclient-1.0.0.dist-info/WHEEL
stitchclient-1.0.0.dist-info/top_level.txt
stitchclient-1.0.0.dist-info/RECORD
