Metadata-Version: 2.1
Name: stitchclient
Version: 1.0.0
Summary: A Stitch API client for Python
Home-page: https://github.com/stitchdata/python-stitch-client
Author: Stitch
Author-email: support@stitchdata.com
License: UNKNOWN
Platform: UNKNOWN
Classifier: Programming Language :: Python :: 3 :: Only
Requires-Dist: msgpack-python
Requires-Dist: python-dateutil (==2.6.1)
Requires-Dist: requests (==2.20.0)
